jupyter_server_mcp/__init__.py
jupyter_server_mcp/extension.py
jupyter_server_mcp/mcp_server.py
jupyter_server_mcp-0.1.1.data/data/etc/jupyter/jupyter_server_config.d/jupyter_server_mcp.json
jupyter_server_mcp-0.1.1.dist-info/METADATA
jupyter_server_mcp-0.1.1.dist-info/WHEEL
jupyter_server_mcp-0.1.1.dist-info/entry_points.txt
jupyter_server_mcp-0.1.1.dist-info/licenses/LICENSE
jupyter_server_mcp-0.1.1.dist-info/RECORD
