Metadata-Version: 2.4
Name: jupyter_server_mcp
Version: 0.1.1
Author-email: Jupyter Developer <jupyter@example.com>
License: BSD 3-Clause License
License-File: LICENSE
Keywords: Extension,FastMCP,Jupyter,MCP
Classifier: Framework :: Jupyter
Classifier: License :: OSI Approved :: BSD License
Classifier: Programming Language :: Python
Classifier: Programming Language :: Python :: 3
Classifier: Programming Language :: Python :: 3.10
Classifier: Programming Language :: Python :: 3.11
Requires-Python: >=3.10
Requires-Dist: fastmcp>=2.0.0
Requires-Dist: jupyter-server<3,>=1.6
Provides-Extra: dev
Requires-Dist: ruff>=0.1.0; extra == 'dev'
Provides-Extra: test
Requires-Dist: pytest-asyncio>=0.21.0; extra == 'test'
Requires-Dist: pytest-jupyter[server]>=0.6; extra == 'test'
Requires-Dist: pytest-mock>=3.10.0; extra == 'test'
Requires-Dist: pytest-tornasync>=0.6.0; extra == 'test'
Requires-Dist: pytest>=7.0; extra == 'test'
